{
  "hash": "3fc211174ff6cb14f1813962059d7eec",
  "result": {
    "markdown": "---\ntitle: \"Visualizando as distribuições\"\nauthor: \"Ricardo Accioly\"\ndate: \"2023-08-24\"\nformat:\n html:\n    code-link: true\n---\n\n\n## Carregando as bibliotecas\n\nVamos trabalhar de novo com os dados do gapminder para fazer algumas visualizações de dados que são muito úteis no dia a dia.\n\nEste material foi adaptado do curso Data Visualization in R with ggplot2 de Kara Woo\n\n\n::: {.cell}\n\n```{.r .cell-code}\nlibrary(\"ggplot2\")\nlibrary(\"dplyr\")\nlibrary(\"gapminder\")\n```\n:::\n\n\n\\newpage\n\n## Selecionando dados\n\n\n::: {.cell}\n\n```{.r .cell-code}\ngap_07 <- filter(gapminder, year == 2007)\n```\n:::\n\n\n## Vendo a distribuição\n\n\n::: {.cell}\n\n```{.r .cell-code}\nggplot(gap_07, aes(x = gdpPercap)) +\n  geom_histogram()\n```\n\n::: {.cell-output .cell-output-stderr}\n```\n`stat_bin()` using `bins = 30`. Pick better value with `binwidth`.\n```\n:::\n\n::: {.cell-output-display}\n![](Aula03_files/figure-html/histograma-1.png){width=672}\n:::\n:::\n\n\n\\newpage\n\n## Criando um histograma usando a regra de Sturges\n\nA regra de Sturges indica 8 faixas enquanto que o padrão do ggplot2 é 30.\n\n\n::: {.cell}\n\n```{.r .cell-code}\nggplot(gap_07, aes(x = gdpPercap)) +\n  geom_histogram(bins = round(1+3.322*log10(nrow(gap_07)),0))\n```\n\n::: {.cell-output-display}\n![](Aula03_files/figure-html/Sturges-1.png){width=672}\n:::\n:::\n\n\n\\newpage\n\n## Criando um gráfico de densidade\n\n\n::: {.cell}\n\n```{.r .cell-code}\nggplot(gap_07, aes(x = gdpPercap)) +\n  geom_density()\n```\n\n::: {.cell-output-display}\n![](Aula03_files/figure-html/densidade-1.png){width=672}\n:::\n:::\n\n\n\\newpage\n\n## Criando um box-plot\n\n\n::: {.cell}\n\n```{.r .cell-code}\nggplot(gap_07, aes(x = continent, y = lifeExp)) +\n  geom_boxplot()\n```\n\n::: {.cell-output-display}\n![](Aula03_files/figure-html/box-plot-1.png){width=672}\n:::\n:::\n\n\n\\newpage\n\n## Criando um box-plot com visão dos dados\n\n\n::: {.cell}\n\n```{.r .cell-code}\nggplot(gap_07, aes(x = continent, y = lifeExp)) +\n  geom_boxplot() +\n  geom_jitter(width = 0.5, alpha = 0.2)\n```\n\n::: {.cell-output-display}\n![](Aula03_files/figure-html/jitter-1.png){width=672}\n:::\n:::\n\n\n\\newpage\n\n## Matriz de Correlações\n\n\n::: {.cell}\n\n```{.r .cell-code}\nlibrary(corrplot)\n```\n\n::: {.cell-output .cell-output-stderr}\n```\ncorrplot 0.92 loaded\n```\n:::\n\n```{.r .cell-code}\ngap_07_s <- gap_07 %>% select(lifeExp, pop, gdpPercap)\nmat_corr <- cor(gap_07_s)\ncorrplot(mat_corr, method = \"number\", col = \"black\", cl.pos = \"n\")\n```\n\n::: {.cell-output-display}\n![](Aula03_files/figure-html/correlações-1.png){width=672}\n:::\n\n```{.r .cell-code}\ncorrplot(mat_corr, method = \"number\")\n```\n\n::: {.cell-output-display}\n![](Aula03_files/figure-html/correlações-2.png){width=672}\n:::\n\n```{.r .cell-code}\ncorrplot(mat_corr)\n```\n\n::: {.cell-output-display}\n![](Aula03_files/figure-html/correlações-3.png){width=672}\n:::\n:::\n\n\n\\newpage\n\n## SPLOM\n\n\n::: {.cell}\n\n```{.r .cell-code}\nlibrary(psych)\n```\n\n::: {.cell-output .cell-output-stderr}\n```\n\nAttaching package: 'psych'\n```\n:::\n\n::: {.cell-output .cell-output-stderr}\n```\nThe following objects are masked from 'package:ggplot2':\n\n    %+%, alpha\n```\n:::\n\n```{.r .cell-code}\npairs.panels(gap_07_s)\n```\n\n::: {.cell-output-display}\n![](Aula03_files/figure-html/splom-1.png){width=672}\n:::\n:::\n\n\n\\newpage\n\n\n::: {.cell}\n\n```{.r .cell-code}\nlibrary(GGally)\n```\n\n::: {.cell-output .cell-output-stderr}\n```\nRegistered S3 method overwritten by 'GGally':\n  method from   \n  +.gg   ggplot2\n```\n:::\n\n```{.r .cell-code}\nggpairs(gap_07_s)\n```\n\n::: {.cell-output-display}\n![](Aula03_files/figure-html/splom2-1.png){width=672}\n:::\n:::\n\n\n\\newpage\n\n## Descrevendo a distribuição\n\n\n::: {.cell}\n\n```{.r .cell-code}\nlibrary(datawizard)\n```\n\n::: {.cell-output .cell-output-stderr}\n```\n\nAttaching package: 'datawizard'\n```\n:::\n\n::: {.cell-output .cell-output-stderr}\n```\nThe following object is masked from 'package:psych':\n\n    rescale\n```\n:::\n\n```{.r .cell-code}\ndescribe_distribution(gap_07_s)\n```\n\n::: {.cell-output .cell-output-stdout}\n```\nVariable  |     Mean |       SD |      IQR |                Range | Skewness | Kurtosis |   n | n_Missing\n---------------------------------------------------------------------------------------------------------\nlifeExp   |    67.01 |    12.07 |    19.59 |       [39.61, 82.60] |    -0.69 |    -0.83 | 142 |         0\npop       | 4.40e+07 | 1.48e+08 | 2.78e+07 | [2.00e+05, 1.32e+09] |     7.40 |    58.33 | 142 |         0\ngdpPercap | 11680.07 | 12859.94 | 16579.19 |   [277.55, 49357.19] |     1.22 |     0.35 | 142 |         0\n```\n:::\n:::\n",
    "supporting": [
      "Aula03_files"
    ],
    "filters": [
      "rmarkdown/pagebreak.lua"
    ],
    "includes": {},
    "engineDependencies": {},
    "preserve": {},
    "postProcess": true
  }
}